obs2org/__init__.py
obs2org/__main__.py
obs2org/convert.py
obs2org/main.py
obs2org/parse_org_mode.py
obs2org-1.3.4.dist-info/LICENSE
obs2org-1.3.4.dist-info/METADATA
obs2org-1.3.4.dist-info/WHEEL
obs2org-1.3.4.dist-info/top_level.txt
obs2org-1.3.4.dist-info/RECORD
