Metadata-Version: 2.1
Name: obs2org
Version: 1.3.4
Summary: Converts Obsidian style markdown files to Org-Mode files using pandoc.
Home-page: https://codeberg.org/Release-Candidate/Obs2Org
Author: Release-Candidate
Author-email: rec@gmx.at
Project-URL: Bug Tracker, https://codeberg.org/Release-Candidate/Obs2Org/issues
Project-URL: Documentation, https://Obs2Org.readthedocs.io/en/latest/
Keywords: markdown,org-mode,obsidian,converter,pandoc
Classifier: Programming Language :: Python :: 3 :: Only
Classifier: Programming Language :: Python :: 3.10
Classifier: License :: OSI Approved :: GNU General Public License v3 or later (GPLv3+)
Classifier: Operating System :: MacOS :: MacOS X
Classifier: Operating System :: Microsoft :: Windows
Classifier: Operating System :: POSIX :: Linux
Classifier: Operating System :: POSIX
Classifier: Operating System :: POSIX :: BSD
Classifier: Operating System :: Unix
Classifier: Operating System :: OS Independent
Classifier: Environment :: Console
Classifier: Development Status :: 5 - Production/Stable
Classifier: Intended Audience :: Developers
Classifier: Intended Audience :: End Users/Desktop
Classifier: Topic :: Text Editors :: Emacs
Classifier: Topic :: Text Processing
Classifier: Topic :: Text Processing :: Markup
Classifier: Topic :: Text Processing :: Markup :: Markdown
Requires-Python: >=3.9
License-File: LICENSE
